README.md
setup.cfg
setup.py
experiment_tracker/Experiment.py
experiment_tracker/__init__.py
experiment_tracker.egg-info/PKG-INFO
experiment_tracker.egg-info/SOURCES.txt
experiment_tracker.egg-info/dependency_links.txt
experiment_tracker.egg-info/requires.txt
experiment_tracker.egg-info/top_level.txt